setup.cfg
setup.py
jupyterhub_swarmspawner.egg-info/PKG-INFO
jupyterhub_swarmspawner.egg-info/SOURCES.txt
jupyterhub_swarmspawner.egg-info/dependency_links.txt
jupyterhub_swarmspawner.egg-info/requires.txt
jupyterhub_swarmspawner.egg-info/top_level.txt
wakonpspawner/__init__.py
wakonpspawner/swarmspawner.py