Metadata-Version: 1.0
Name: jupyterhub-swarmspawner
Version: 1.1
Summary: SwarmSpawner: A spawner for JupyterHub that uses Docker Swarm s services
Home-page: https://github.com/wakonp/SwarmSpawner/
Author: Philipp Wakonigg
Author-email: philipp.wakonigg@edu.fh-joanneum.at
License: BSD
Platform: UNKNOWN
